dpaycli/__init__.py
dpaycli/__main__.py
dpaycli/ui.py
dpaycli-0.1.7.dist-info/METADATA
dpaycli-0.1.7.dist-info/RECORD
dpaycli-0.1.7.dist-info/WHEEL
dpaycli-0.1.7.dist-info/entry_points.txt
dpaycli-0.1.7.dist-info/top_level.txt
