Metadata-Version: 2.1
Name: dpaycli
Version: 0.1.7
Summary: Command line tool to interface with the dPay network
Home-page: http://library.dpays.io/dpaycli
Author: Jared Rice Sr.
Author-email: <jared@benchx.io>
Maintainer: Jared Rice Sr.
Maintainer-email: <jared@benchx.io>
License: UNKNOWN
Download-URL: https://github.com/dpays/dpaycli/tarball/0.1.7
Keywords: dpay,library,api,rpc,cli
Platform: UNKNOWN
Classifier: License :: OSI Approved :: MIT License
Classifier: Operating System :: OS Independent
Classifier: Programming Language :: Python :: 3
Classifier: Development Status :: 3 - Alpha
Classifier: Intended Audience :: Developers
Requires-Dist: dpay-lib (>=0.1.4)
Requires-Dist: prettytable (==0.7.2)
Requires-Dist: colorama (==0.3.6)
